pdm-2.26.5.dist-info/METADATA
pdm-2.26.5.dist-info/WHEEL
pdm-2.26.5.dist-info/entry_points.txt
pdm-2.26.5.dist-info/licenses/LICENSE
pdm/VERSION
pdm/__init__.py
pdm/__main__.py
pdm/__version__.py
pdm/_types.py
pdm/builders/__init__.py
pdm/builders/base.py
pdm/builders/editable.py
pdm/builders/sdist.py
pdm/builders/wheel.py
pdm/cli/__init__.py
pdm/cli/actions.py
pdm/cli/commands/__init__.py
pdm/cli/commands/add.py
pdm/cli/commands/base.py
pdm/cli/commands/build.py
pdm/cli/commands/cache.py
pdm/cli/commands/completion.py
pdm/cli/commands/config.py
pdm/cli/commands/export.py
pdm/cli/commands/fix/__init__.py
pdm/cli/commands/fix/fixers.py
pdm/cli/commands/import_cmd.py
pdm/cli/commands/info.py
pdm/cli/commands/init.py
pdm/cli/commands/install.py
pdm/cli/commands/list.py
pdm/cli/commands/lock.py
pdm/cli/commands/new.py
pdm/cli/commands/outdated.py
pdm/cli/commands/publish/__init__.py
pdm/cli/commands/publish/package.py
pdm/cli/commands/publish/repository.py
pdm/cli/commands/python.py
pdm/cli/commands/remove.py
pdm/cli/commands/run.py
pdm/cli/commands/search.py
pdm/cli/commands/self_cmd.py
pdm/cli/commands/show.py
pdm/cli/commands/sync.py
pdm/cli/commands/update.py
pdm/cli/commands/use.py
pdm/cli/commands/venv/__init__.py
pdm/cli/commands/venv/activate.py
pdm/cli/commands/venv/backends.py
pdm/cli/commands/venv/create.py
pdm/cli/commands/venv/list.py
pdm/cli/commands/venv/purge.py
pdm/cli/commands/venv/remove.py
pdm/cli/commands/venv/utils.py
pdm/cli/completions/__init__.py
pdm/cli/completions/pdm.bash
pdm/cli/completions/pdm.fish
pdm/cli/completions/pdm.ps1
pdm/cli/completions/pdm.zsh
pdm/cli/filters.py
pdm/cli/hooks.py
pdm/cli/options.py
pdm/cli/templates/__init__.py
pdm/cli/templates/default/.gitignore
pdm/cli/templates/default/README.md
pdm/cli/templates/default/__init__.py
pdm/cli/templates/default/pyproject.toml
pdm/cli/templates/default/src/example_package/__init__.py
pdm/cli/templates/default/tests/__init__.py
pdm/cli/templates/minimal/.gitignore
pdm/cli/templates/minimal/__init__.py
pdm/cli/templates/minimal/pyproject.toml
pdm/cli/utils.py
pdm/compat.py
pdm/core.py
pdm/environments/__init__.py
pdm-2.26.5.dist-info/RECORD
