Metadata-Version: 2.4
Name: pdm
Version: 2.26.5
Summary: A modern Python package and dependency manager supporting the latest PEP standards
Keywords: packaging,dependency,workflow
Author-Email: Frost Ming <mianghong@gmail.com>
License-Expression: MIT
License-File: LICENSE
Classifier: Topic :: Software Development :: Build Tools
Classifier: Programming Language :: Python :: 3
Classifier: Programming Language :: Python :: 3.9
Classifier: Programming Language :: Python :: 3.10
Classifier: Programming Language :: Python :: 3.11
Classifier: Programming Language :: Python :: 3.12
Classifier: Programming Language :: Python :: 3.13
Project-URL: Homepage, https://pdm-project.org
Project-URL: Repository, https://github.com/pdm-project/pdm
Project-URL: Documentation, https://pdm-project.org
Project-URL: Changelog, https://pdm-project.org/latest/dev/changelog/
Requires-Python: >=3.9
Requires-Dist: blinker
Requires-Dist: packaging>22.0
Requires-Dist: platformdirs
Requires-Dist: rich>=12.3.0
Requires-Dist: virtualenv>=20
Requires-Dist: pyproject-hooks
Requires-Dist: unearth>=0.17.5
Requires-Dist: dep-logic>=0.5
Requires-Dist: findpython<1.0.0a0,>=0.7.0
Requires-Dist: tomlkit<1,>=0.11.1
Requires-Dist: shellingham>=1.3.2
Requires-Dist: python-dotenv>=0.15
Requires-Dist: resolvelib>=1.1
Requires-Dist: installer<0.8,>=0.7
Requires-Dist: truststore>=0.10.4; python_version >= "3.10"
Requires-Dist: tomli>=1.1.0; python_version < "3.11"
Requires-Dist: importlib-metadata>=3.6; python_version < "3.10"
Requires-Dist: hishel[httpx]>=1.0.0
Requires-Dist: pbs-installer>=2025.10.7
Requires-Dist: httpx[socks]<1,>0.20
Requires-Dist: filelock>=3.13
Requires-Dist: httpcore>=1.0.6
Requires-Dist: certifi>=2024.8.30
Requires-Dist: id>=1.5.0
Provides-Extra: pytest
Requires-Dist: pytest; extra == "pytest"
Requires-Dist: pytest-mock; extra == "pytest"
Provides-Extra: copier
Requires-Dist: copier>=8.0.0; extra == "copier"
Provides-Extra: cookiecutter
Requires-Dist: cookiecutter; extra == "cookiecutter"
Provides-Extra: keyring
Requires-Dist: keyring; extra == "keyring"
Provides-Extra: template
Requires-Dist: pdm[cookiecutter,copier]; extra == "template"
Provides-Extra: all
Requires-Dist: pdm[keyring,template]; extra == "all"
Provides-Extra: locked
Requires-Dist: anyio==4.12.0; extra == "locked"
Requires-Dist: anysqlite==0.0.5; extra == "locked"
Requires-Dist: blinker==1.9.0; extra == "locked"
Requires-Dist: certifi==2025.11.12; extra == "locked"
Requires-Dist: charset-normalizer==3.4.4; extra == "locked"
Requires-Dist: dep-logic==0.5.2; extra == "locked"
Requires-Dist: distlib==0.4.0; extra == "locked"
Requires-Dist: exceptiongroup==1.3.1; python_version < "3.11" and extra == "locked"
Requires-Dist: filelock==3.19.1; extra == "locked"
Requires-Dist: findpython==0.7.1; extra == "locked"
Requires-Dist: h11==0.16.0; extra == "locked"
Requires-Dist: hishel==1.1.8; extra == "locked"
Requires-Dist: hishel[httpx]==1.1.8; extra == "locked"
Requires-Dist: httpcore==1.0.9; extra == "locked"
Requires-Dist: httpx==0.28.1; extra == "locked"
Requires-Dist: httpx[socks]==0.28.1; extra == "locked"
Requires-Dist: id==1.5.0; extra == "locked"
Requires-Dist: idna==3.11; extra == "locked"
Requires-Dist: importlib-metadata==8.7.0; python_version < "3.12" and extra == "locked"
Requires-Dist: installer==0.7.0; extra == "locked"
Requires-Dist: markdown-it-py==3.0.0; extra == "locked"
Requires-Dist: mdurl==0.1.2; extra == "locked"
Requires-Dist: msgpack==1.1.2; extra == "locked"
Requires-Dist: packaging==25.0; extra == "locked"
Requires-Dist: pbs-installer==2025.12.5; extra == "locked"
Requires-Dist: platformdirs==4.4.0; extra == "locked"
Requires-Dist: pygments==2.19.2; extra == "locked"
Requires-Dist: pyproject-hooks==1.2.0; extra == "locked"
Requires-Dist: python-dotenv==1.2.1; extra == "locked"
Requires-Dist: requests==2.32.5; extra == "locked"
Requires-Dist: resolvelib==1.2.1; extra == "locked"
Requires-Dist: rich==14.2.0; extra == "locked"
Requires-Dist: shellingham==1.5.4; extra == "locked"
Requires-Dist: socksio==1.0.0; extra == "locked"
Requires-Dist: tomli==2.3.0; python_version < "3.11" and extra == "locked"
Requires-Dist: tomlkit==0.13.3; extra == "locked"
Requires-Dist: truststore==0.10.4; python_version >= "3.10" and extra == "locked"
Requires-Dist: typing-extensions==4.15.0; extra == "locked"
Requires-Dist: unearth==0.18.1; extra == "locked"
Requires-Dist: urllib3==2.6.2; extra == "locked"
Requires-Dist: virtualenv==20.35.4; extra == "locked"
Requires-Dist: zipp==3.23.0; python_version < "3.12" and extra == "locked"
Provides-Extra: all-locked
Requires-Dist: backports-tarfile==1.2.0; python_version < "3.12" and extra == "all-locked"
Requires-Dist: cffi==2.0.0; platform_python_implementation != "PyPy" and sys_platform == "linux" and extra == "all-locked"
Requires-Dist: cryptography==43.0.3; sys_platform == "linux" and extra == "all-locked"
Requires-Dist: importlib-metadata==8.7.0; python_version < "3.12" and extra == "all-locked"
Requires-Dist: jaraco-classes==3.4.0; extra == "all-locked"
Requires-Dist: jaraco-context==6.0.1; extra == "all-locked"
Requires-Dist: jaraco-functools==4.3.0; extra == "all-locked"
Requires-Dist: jeepney==0.9.0; sys_platform == "linux" and extra == "all-locked"
Requires-Dist: keyring==25.7.0; extra == "all-locked"
Requires-Dist: more-itertools==10.8.0; extra == "all-locked"
Requires-Dist: pycparser==2.23; platform_python_implementation != "PyPy" and sys_platform == "linux" and implementation_name != "PyPy" and extra == "all-locked"
Requires-Dist: pywin32-ctypes==0.2.3; sys_platform == "win32" and extra == "all-locked"
Requires-Dist: secretstorage==3.3.3; sys_platform == "linux" and extra == "all-locked"
Requires-Dist: zipp==3.23.0; python_version < "3.12" and extra == "all-locked"
